uniplate.py
uniplate-0.0.3.dist-info/METADATA
uniplate-0.0.3.dist-info/WHEEL
uniplate-0.0.3.dist-info/top_level.txt
uniplate-0.0.3.dist-info/RECORD
