Metadata-Version: 2.1
Name: uniplate
Version: 0.0.3
Summary: Python generics library using combinators from haskell's uniplate
Home-page: https://github.com/edwardgeorge/uniplate
Author: Edward George
Author-email: edwardgeorge@gmail.com
License: UNKNOWN
Platform: UNKNOWN
Classifier: Development Status :: 3 - Alpha
Classifier: Intended Audience :: Developers
Classifier: Programming Language :: Python :: 3
Classifier: Programming Language :: Python :: 3.6
Classifier: Programming Language :: Python :: 2.7
Classifier: Programming Language :: Python
